spafe/__init__.py
spafe/version.py
spafe/fbanks/__init__.py
spafe/fbanks/bark_fbanks.py
spafe/fbanks/gammatone_fbanks.py
spafe/fbanks/linear_fbanks.py
spafe/fbanks/mel_fbanks.py
spafe/features/__init__.py
spafe/features/bfcc.py
spafe/features/cqcc.py
spafe/features/gfcc.py
spafe/features/lfcc.py
spafe/features/lpc.py
spafe/features/mfcc.py
spafe/features/msrcc.py
spafe/features/ngcc.py
spafe/features/pncc.py
spafe/features/psrcc.py
spafe/features/rplp.py
spafe/features/spfeats.py
spafe/frequencies/__init__.py
spafe/frequencies/dominant_frequencies.py
spafe/frequencies/fundamental_frequencies.py
spafe/utils/__init__.py
spafe/utils/cepstral.py
spafe/utils/converters.py
spafe/utils/exceptions.py
spafe/utils/filters.py
spafe/utils/preprocessing.py
spafe/utils/spectral.py
spafe/utils/vis.py
tests/__init__.py
tests/conftest.py
tests/test_fbanks_bark.py
tests/test_fbanks_gamma.py
tests/test_fbanks_lin.py
tests/test_fbanks_mel.py
tests/test_features_bfcc.py
tests/test_features_cqcc.py
tests/test_features_gfcc.py
tests/test_features_lfcc.py
tests/test_features_lpcc.py
tests/test_features_mfcc.py
tests/test_features_msrcc.py
tests/test_features_ngcc.py
tests/test_features_pncc.py
tests/test_features_psrcc.py
tests/test_features_rplp.py
tests/test_frequencies.py
tests/test_utils_cepstral.py
tests/test_utils_converters.py
tests/test_utils_filters.py
tests/test_utils_preprocessing.py
tests/test_utils_spectral.py
tests/test_utils_vis.py
spafe-0.3.3.dist-info/LICENSE
spafe-0.3.3.dist-info/METADATA
spafe-0.3.3.dist-info/WHEEL
spafe-0.3.3.dist-info/top_level.txt
spafe-0.3.3.dist-info/RECORD
