Metadata-Version: 2.1
Name: spafe
Version: 0.3.3
Summary: Simplified Python Audio-Features Extraction.
Home-page: https://github.com/SuperKogito/spafe
Author: Ayoub Malek
Author-email: superkogito@gmail.com
Maintainer: Ayoub Malek
Maintainer-email: superkogito@gmail.com
License: BSD
Keywords: audio processing,features extraction
Platform: any
Classifier: Development Status :: 3 - Alpha
Classifier: Environment :: Console
Classifier: Intended Audience :: Developers
Classifier: License :: OSI Approved :: BSD License
Classifier: Operating System :: OS Independent
Classifier: Programming Language :: Python
Classifier: Topic :: Multimedia :: Sound/Audio :: Analysis
Classifier: Topic :: Multimedia :: Sound/Audio :: Editors
Classifier: Topic :: Multimedia :: Sound/Audio :: Speech
Classifier: Topic :: Scientific/Engineering :: Information Analysis
Classifier: Topic :: Scientific/Engineering :: Artificial Intelligence
License-File: LICENSE
Requires-Dist: numpy >=1.21
Requires-Dist: scipy >=1.7.3
Requires-Dist: typing-extensions
Provides-Extra: docs
Requires-Dist: sphinxcontrib-napoleon ==0.7 ; extra == 'docs'
Requires-Dist: nbsphinx ==0.8.9 ; extra == 'docs'
Requires-Dist: pydata-sphinx-theme ==0.8.1 ; extra == 'docs'
Requires-Dist: matplotlib ; extra == 'docs'
Provides-Extra: plotting
Requires-Dist: maplotlib ; extra == 'plotting'
Provides-Extra: tests
Requires-Dist: pytest >=6.2.4 ; extra == 'tests'
Requires-Dist: pytest-cov ; extra == 'tests'
Requires-Dist: codecov ; extra == 'tests'
Requires-Dist: coveralls ; extra == 'tests'
Requires-Dist: pytest-xdist ; extra == 'tests'
Requires-Dist: codacy-coverage ; extra == 'tests'
Requires-Dist: matplotlib ; extra == 'tests'
Requires-Dist: mock ==4.0.3 ; extra == 'tests'
